{"timestamp": "2026-05-12 09:55", "price": 0.5879, "price_change_pct": 10.508, "volume_24h": 11.09, "oi_usdt": 17.76, "oi_coin": 30214561.0, "funding_rate": 0.046141, "sm_total_traders": 503, "sm_long_traders": 295, "sm_short_traders": 208, "sm_long_whales": 143, "sm_short_whales": 72, "sm_long_pos_usdt": 10.04, "sm_short_pos_usdt": 1.13, "sm_ls_ratio": 8.8921, "sm_long_avg_price": 0.5248, "sm_short_avg_price": 0.5182, "sm_long_profit_pct": 81.4, "sm_short_profit_pct": 3.8, "sm30_long_traders": 115, "sm30_short_traders": 90, "sm30_long_whales": 65, "sm30_short_whales": 71, "sm30_long_pos_usdt": 51.1, "sm30_short_pos_usdt": 131.5, "global_ls_ratio": 1.0317, "top_pos_ls_ratio": 1.9436, "onchain_holders": 141193, "onchain_top10_pct": 84.43, "onchain_kol_holders": 4, "onchain_sm_holders": 9, "onchain_liquidity": 1.33, "taker_buy_sell_ratio": 1.0334, "taker_buy_vol": 0.29, "taker_sell_vol": 0.28, "depth_bid_total_k": 8.7, "depth_ask_total_k": 10.6, "depth_bid_wall_price": 0.5853, "depth_bid_wall_qty": 2449, "depth_ask_wall_price": 0.5889, "depth_ask_wall_qty": 2952, "depth_ratio": 0.82, "tape_large_count": 0, "tape_medium_count": 0, "tape_large_buy": 0, "tape_large_sell": 0, "tape_aggr_buy_k": 18.6, "tape_aggr_sell_k": 6.7, "btc_price": 81141.0, "btc_24h_pct": -0.38, "river_vs_btc": 10.89}