{"timestamp": "2026-05-12 09:15", "price": 0.02735, "price_change_pct": 4.032, "volume_24h": 15.54, "oi_usdt": 11.27, "oi_coin": 412185316.0, "funding_rate": 0.02011, "sm_total_traders": 570, "sm_long_traders": 274, "sm_short_traders": 296, "sm_long_whales": 79, "sm_short_whales": 138, "sm_long_pos_usdt": 1.72, "sm_short_pos_usdt": 1.34, "sm_ls_ratio": 1.2881, "sm_long_avg_price": 0.0292, "sm_short_avg_price": 0.0277, "sm_long_profit_pct": 57.3, "sm_short_profit_pct": 19.6, "sm30_long_traders": 76, "sm30_short_traders": 48, "sm30_long_whales": 44, "sm30_short_whales": 35, "sm30_long_pos_usdt": 29.6, "sm30_short_pos_usdt": 16.8, "global_ls_ratio": 2.7707, "top_pos_ls_ratio": 1.6876, "taker_buy_sell_ratio": 0.9856, "taker_buy_vol": 0.52, "taker_sell_vol": 0.53, "depth_bid_total_k": 93.9, "depth_ask_total_k": 67.4, "depth_bid_wall_price": 0.0272, "depth_bid_wall_qty": 375954, "depth_ask_wall_price": 0.02741, "depth_ask_wall_qty": 236859, "depth_ratio": 1.39, "tape_large_count": 0, "tape_medium_count": 0, "tape_large_buy": 0, "tape_large_sell": 0, "tape_aggr_buy_k": 29.7, "tape_aggr_sell_k": 30.4, "btc_price": 81339.0, "btc_24h_pct": -0.16, "river_vs_btc": 4.19}